wmpy_power/__init__.py
wmpy_power/model.py
wmpy_power/sce_ua.py
wmpy_power/tests.py
wmpy_power/utilities.py
wmpy_power-1.0.3.dist-info/LICENSE
wmpy_power-1.0.3.dist-info/METADATA
wmpy_power-1.0.3.dist-info/WHEEL
wmpy_power-1.0.3.dist-info/entry_points.txt
wmpy_power-1.0.3.dist-info/top_level.txt
wmpy_power-1.0.3.dist-info/zip-safe
wmpy_power-1.0.3.dist-info/RECORD
