Metadata-Version: 2.1
Name: wmpy_power
Version: 1.0.3
Summary: Estimates hydropower generation accounting for operating constraints and electricity grid operations.
License: { file = "LICENSE" }
Keywords: hydropower,water
Classifier: Programming Language :: Python :: 3
Requires-Python: <3.12,>=3.9
License-File: LICENSE
Requires-Dist: duckdb >=0.4.0
Requires-Dist: matplotlib >=3.5.2
Requires-Dist: openpyxl >=3.0.10
Requires-Dist: pandas >=1.4.2
Requires-Dist: psutil >=5.9.1
Requires-Dist: pyarrow >=8.0.0
Requires-Dist: pyyaml >=6.0
Requires-Dist: scipy >=1.8.1
Requires-Dist: tqdm >=4.65.0
Requires-Dist: jupyter >=1.0.0
Provides-Extra: dev
Requires-Dist: black >=22.3.0 ; extra == 'dev'
Requires-Dist: build >=1.1.1 ; extra == 'dev'
Requires-Dist: twine >=5.0.0 ; extra == 'dev'
